usbmuxctl/__init__.py
usbmuxctl/__main__.py
usbmuxctl/update.py
usbmuxctl/usbmuxctl.py
usbmuxctl/firmware/__init__.py
usbmuxctl/firmware/umx-T03_0.1.2.bin
usbmuxctl/firmware/version.py
usbmuxctl-0.1.4.dist-info/COPYING
usbmuxctl-0.1.4.dist-info/METADATA
usbmuxctl-0.1.4.dist-info/WHEEL
usbmuxctl-0.1.4.dist-info/entry_points.txt
usbmuxctl-0.1.4.dist-info/top_level.txt
usbmuxctl-0.1.4.dist-info/RECORD
