Metadata-Version: 2.1
Name: usbmuxctl
Version: 0.1.4
Summary: Tool to control an USB-Mux from the command line
Author-email: Chris Fiege <python@pengutronix.de>
License: LGPL-2.1-or-later
Project-URL: homepage, https://github.com/linux-automation/usbmuxctl
Project-URL: documentation, https://linux-automation.com/umx-M01/
Classifier: Environment :: Console
Classifier: Natural Language :: English
Classifier: Operating System :: Unix
Classifier: Programming Language :: Python :: 3 :: Only
License-File: COPYING
Requires-Dist: pyusb
Requires-Dist: termcolor
